unsupervised_model/VERSION
unsupervised_model/__init__.py
unsupervised_model/config.yml
unsupervised_model/pipeline.py
unsupervised_model/predict.py
unsupervised_model/train_pipeline.py
unsupervised_model/config/__init__.py
unsupervised_model/config/core.py
unsupervised_model/datasets/Country-data.csv
unsupervised_model/datasets/__init__.py
unsupervised_model/processing/__init__.py
unsupervised_model/processing/data_manager.py
unsupervised_model/trained_models/__init__.py
unsupervised_model/trained_models/unsupervised_model_output_v0.0.1.pkl
unsupervised_model_pipe-0.0.1.dist-info/METADATA
unsupervised_model_pipe-0.0.1.dist-info/WHEEL
unsupervised_model_pipe-0.0.1.dist-info/top_level.txt
unsupervised_model_pipe-0.0.1.dist-info/RECORD
